{
  "compound_name": "cystine",
  "descriptions": [
    {
      "description": "シスチンは、脂質をエネルギー源として利用しやすくすることで、運動中の疲労を軽減し、持久力をサポートしてくれるからだよ！💪このアミノ酸は、体内でエネルギー源となるものを増やしたり、運動中の「きつい！」と感じるのを和らげてくれたりするんだ。✨実は、シスチンは髪の毛や爪を強くするのにも役立つと言われているんだぜ！😉",
      "timestamp": "2025-10-21T19:26:20.875069"
    },
    {
      "description": "持久力をアップさせたいなら、シスチンがおすすめだよ！✨ この分子は、エネルギーを作り出すミトコンドリアの働きを助けて、脂質を上手に使うのをサポートしてくれるんだ。しかも、運動中の疲れを軽減する効果もあるんだぜ！💪",
      "timestamp": "2025-10-21T20:02:38.080579"
    },
    {
      "description": "シスチンは、ミトコンドリアの働きを促進し、エネルギー源を増やすことで、持久力の向上に直接的に関与する分子だよ。\nシスチンはアミノ酸の一種で、体内のエネルギー産生を助け、運動時の疲労感を軽減する効果が期待できるんだ。\nシスチンは、毛髪や爪にも含まれる成分で、美容にも良いと言われているんだぜ！✨",
      "timestamp": "2025-10-21T20:08:13.146210"
    }
  ],
  "timestamp": "2025-10-21T20:08:13.146225"
}