{
  "compound_name": "penicillin",
  "similar_compounds": [
    {
      "compound_name": "amoxicillin",
      "name_jp": "アモキシシリン",
      "timestamp": "2025-10-21T20:00:33.901188",
      "descriptions": [
        {
          "description": "アモキシシリンは、ペニシリンと同じくβ-ラクタム環を持つ仲間で、構造が似ているんだ。細菌の細胞壁を作るのを邪魔して、バイキンをやっつける働きがあるよ antibiotikum 🦠。風邪やのどの痛みなど、色々な感染症の治療に使われているんだぜ。",
          "timestamp": "2025-10-21T19:26:52.067705"
        },
        {
          "description": "アモキシシリンはペニシリンの仲間で、同じように細菌をやっつける働きがあるんだ💪。風邪や中耳炎など、色々なバイキンをやっつけるのに使われていて、お医者さんもよく処方してくれるよ💊✨。実は、アモキシシリンはペニシリンよりも体に吸収されやすくて、より効果的にバイキンをやっつけられるように改良された、すごい薬なんだぜ🔬！",
          "timestamp": "2025-10-21T20:00:33.901188"
        }
      ],
      "japanese_name": "アモキシシリン"
    },
    {
      "compound_name": "ampicillin",
      "name_jp": "アンピシリン",
      "timestamp": "2025-10-21T20:00:55.395291",
      "descriptions": [
        {
          "description": "アンピシリンはペニシリンの仲間で、細菌をやっつけるのに使われる薬だよ💊。風邪やのどの痛みなど、色々な病気の原因になる細菌を退治してくれるんだ✨。実は、アンピシリンはペニシリンの仲間の中でも、色々な種類の細菌に効くように改良された「パワーアップ版」なんだぜ💪！",
          "timestamp": "2025-10-21T19:29:11.749653"
        },
        {
          "description": "アンピシリンはペニシリンと似た構造を持つ仲間だよ💊。細菌の細胞壁を作るのを邪魔して、バイキンをやっつけるんだ💪。ペニシリンよりも広範囲のバイキンに効く、スーパーヒーローなんだぜ✨！",
          "timestamp": "2025-10-21T20:00:55.395291"
        }
      ],
      "japanese_name": "アンピシリン"
    },
    {
      "compound_name": "cephalosporin",
      "name_jp": "セファロスポリン",
      "timestamp": "2025-10-21T20:02:22.302576",
      "descriptions": [
        {
          "description": "セファロスポリンは、ペニシリンと同じくβ-ラクタム環を持つ仲間だよ！ 構造が似ているから、細菌の細胞壁を作るのを邪魔して、バイキンをやっつける働きをするんだ💪。 ペニシリンよりも効き目が強かったり、効くバイキンの種類が多かったりする、いわばペニシリンのパワーアップ版なんだぜ✨。",
          "timestamp": "2025-10-21T20:02:22.302576"
        }
      ],
      "japanese_name": "セファロスポリン"
    },
    {
      "compound_name": "cephalexin",
      "name_jp": "セファレキシン",
      "timestamp": "2025-10-21T20:24:11.230410",
      "descriptions": [
        {
          "description": "セファレキシンは、ペニシリンと同じく細菌の細胞壁合成を邪魔する仲間だよ💊構造が似ているから、ペニシリンが効かない細菌にも効果があることがあるんだ！セファレキシンは、人間だけでなくワンちゃんやネコちゃんの病気を治すためにも使われている、とっても頼りになるお薬なんだよ🐶🐱",
          "timestamp": "2025-10-21T20:24:11.230410"
        }
      ],
      "japanese_name": "セファレキシン"
    }
  ],
  "timestamp": "2025-10-21T20:24:17.883968"
}