{
  "compound_name": "vitamine",
  "descriptions": [
    {
      "description": "ビタミンEは、**分子量**が`430.70`で、**重原子数**が`31`だから、比較的大型の分子だね！💪\n\n**LogP**が`10.70`と非常に高い値を示しているから、油に溶けやすい性質（脂溶性）がとても強いと考えられるよ。これは、細胞の膜を通り抜けやすいことを意味しているんだ。🪞✨\n一方で、**TPSA**は`29.5` Å²と小さい値だから、これも膜透過性の高さを後押ししている可能性があるね。脳のバリアを越えるのも得意かもしれないぜ！🧠🚀\n\n**水素結合供与体数**が`1`、**水素結合受容体数**が`2`だから、水には溶けにくいけれど、油っぽい環境では安定して存在できる性質を持っていると考えられるよ。💧🙅‍♀️\n\n**分子複雑度**が`503.0`と高く、**回転可能結合数**が`12`と多いことから、構造が複雑で柔軟性があることがわかるね。この複雑で柔軟な構造が、体内の様々な細胞や分子と特異的に相互作用し、強力な抗酸化作用を発揮するのに役立っているのかもしれないんだ。 antioxidante 💪🛡️\nビタミンEは、体内で発生する有害な活性酸素から細胞を守る「抗酸化作用」で有名だよね。この高い脂溶性と膜透過性のおかげで、細胞膜に豊富に存在し、脂質を酸化から守る重要な役割を果たしているんだ。まさに、体のガードマンだね！🛡️✨",
      "timestamp": "2025-10-21T19:17:05.034488"
    }
  ],
  "timestamp": "2025-10-21T19:17:05.034537"
}